Metadata-Version: 2.1
Name: py-taos
Version: 2.0.3.1
Summary: TDengine python client package
Home-page: https://gitee.com/evoup/py-taos
Author: Taosdata Inc.
Author-email: support@taosdata.com
License: UNKNOWN
Platform: UNKNOWN
Classifier: Programming Language :: Python :: 3
Classifier: Operating System :: POSIX :: Linux
